payi/__init__.py
payi/_base_client.py
payi/_client.py
payi/_compat.py
payi/_constants.py
payi/_exceptions.py
payi/_files.py
payi/_models.py
payi/_qs.py
payi/_resource.py
payi/_response.py
payi/_streaming.py
payi/_types.py
payi/_version.py
payi/pagination.py
payi/py.typed
payi/_utils/__init__.py
payi/_utils/_compat.py
payi/_utils/_datetime_parse.py
payi/_utils/_logs.py
payi/_utils/_proxy.py
payi/_utils/_reflection.py
payi/_utils/_resources_proxy.py
payi/_utils/_streams.py
payi/_utils/_sync.py
payi/_utils/_transform.py
payi/_utils/_typing.py
payi/_utils/_utils.py
payi/lib/.keep
payi/lib/AnthropicInstrumentor.py
payi/lib/BedrockInstrumentor.py
payi/lib/GoogleGenAiInstrumentor.py
payi/lib/OpenAIInstrumentor.py
payi/lib/ProviderRequest.py
payi/lib/Stopwatch.py
payi/lib/StreamWrappers.py
payi/lib/VertexInstrumentor.py
payi/lib/VertexRequest.py
payi/lib/helpers.py
payi/lib/instrument.py
payi/lib/version_helper.py
payi/lib/data/cohere_embed_english_v3.json
payi/resources/__init__.py
payi/resources/ingest.py
payi/resources/categories/__init__.py
payi/resources/categories/categories.py
payi/resources/categories/resources.py
payi/resources/limits/__init__.py
payi/resources/limits/limits.py
payi/resources/limits/properties.py
payi/resources/requests/__init__.py
payi/resources/requests/requests.py
payi/resources/requests/request_id/__init__.py
payi/resources/requests/request_id/properties.py
payi/resources/requests/request_id/request_id.py
payi/resources/requests/request_id/result.py
payi/resources/requests/response_id/__init__.py
payi/resources/requests/response_id/properties.py
payi/resources/requests/response_id/response_id.py
payi/resources/requests/response_id/result.py
payi/resources/use_cases/__init__.py
payi/resources/use_cases/kpis.py
payi/resources/use_cases/properties.py
payi/resources/use_cases/use_cases.py
payi/resources/use_cases/definitions/__init__.py
payi/resources/use_cases/definitions/definitions.py
payi/resources/use_cases/definitions/kpis.py
payi-0.1.0a154.dist-info/METADATA
payi-0.1.0a154.dist-info/WHEEL
payi-0.1.0a154.dist-info/licenses/LICENSE
payi-0.1.0a154.dist-info/RECORD
