Metadata-Version: 2.3
Name: payi
Version: 0.1.0a154
Summary: The official Python library for the payi API
Project-URL: Homepage, https://github.com/Pay-i/pay-i-python
Project-URL: Repository, https://github.com/Pay-i/pay-i-python
Author-email: Payi <support@payi.com>
License: Apache-2.0
Classifier: Intended Audience :: Developers
Classifier: License :: OSI Approved :: Apache Software License
Classifier: Operating System :: MacOS
Classifier: Operating System :: Microsoft :: Windows
Classifier: Operating System :: OS Independent
Classifier: Operating System :: POSIX
Classifier: Operating System :: POSIX :: Linux
Classifier: Programming Language :: Python :: 3.9
Classifier: Programming Language :: Python :: 3.10
Classifier: Programming Language :: Python :: 3.11
Classifier: Programming Language :: Python :: 3.12
Classifier: Programming Language :: Python :: 3.13
Classifier: Programming Language :: Python :: 3.14
Classifier: Topic :: Software Development :: Libraries :: Python Modules
Classifier: Typing :: Typed
Requires-Python: >=3.9
Requires-Dist: anyio<5,>=3.5.0
Requires-Dist: distro<2,>=1.7.0
Requires-Dist: httpx<1,>=0.23.0
Requires-Dist: nest-asyncio>=1.6.0
Requires-Dist: pydantic<3,>=1.9.0
Requires-Dist: sniffio
Requires-Dist: tiktoken>=0.8.0
Requires-Dist: tokenizers>=0.21.4
Requires-Dist: typing-extensions<5,>=4.10
Requires-Dist: wrapt>=1.17.2
Provides-Extra: aiohttp
Requires-Dist: aiohttp; extra == 'aiohttp'
Requires-Dist: httpx-aiohttp>=0.1.9; extra == 'aiohttp'
